odoo/addons/purchase_order_report_grouped_by_vendor/README.rst
odoo/addons/purchase_order_report_grouped_by_vendor/__init__.py
odoo/addons/purchase_order_report_grouped_by_vendor/__manifest__.py
odoo/addons/purchase_order_report_grouped_by_vendor/i18n/es.po
odoo/addons/purchase_order_report_grouped_by_vendor/i18n/it.po
odoo/addons/purchase_order_report_grouped_by_vendor/i18n/purchase_order_report_grouped_by_vendor.pot
odoo/addons/purchase_order_report_grouped_by_vendor/models/__init__.py
odoo/addons/purchase_order_report_grouped_by_vendor/models/purchase_order.py
odoo/addons/purchase_order_report_grouped_by_vendor/readme/CONTRIBUTORS.md
odoo/addons/purchase_order_report_grouped_by_vendor/readme/DESCRIPTION.md
odoo/addons/purchase_order_report_grouped_by_vendor/readme/USAGE.md
odoo/addons/purchase_order_report_grouped_by_vendor/static/description/icon.png
odoo/addons/purchase_order_report_grouped_by_vendor/static/description/index.html
odoo/addons/purchase_order_report_grouped_by_vendor/tests/__init__.py
odoo/addons/purchase_order_report_grouped_by_vendor/tests/test_purchase_order_report_grouped_by_vendor.py
odoo/addons/purchase_order_report_grouped_by_vendor/views/report_purchase_order.xml
odoo_addon_purchase_order_report_grouped_by_vendor-17.0.1.0.0.4.dist-info/METADATA
odoo_addon_purchase_order_report_grouped_by_vendor-17.0.1.0.0.4.dist-info/WHEEL
odoo_addon_purchase_order_report_grouped_by_vendor-17.0.1.0.0.4.dist-info/top_level.txt
odoo_addon_purchase_order_report_grouped_by_vendor-17.0.1.0.0.4.dist-info/RECORD
